[
 {
   "id": 1,
   "ordem": "Columbiformes",
   "familia": "Columbidae",
   "nomeCientifico": "Columba livia",
   "nomeComumBrasileiro": "pombo-doméstico",
   "descricao": "Gmelin, 1789",
   "nomeComumIngles": "Rock Pigeon",
   "periodoAtividade": "Diurno",
   "dimorfismo": "Não",
   "estadoConservacaoIucn": "Pouco Preocupante",
   "endemicaBrasil": "Não",
   "habitats": "Áreas urbanas, Áreas rurais, Ambientes antrópicos (plantios, jardins, construções)",
   "dieta": "Sementes, Frutos",
   "particula": "pombo-domestico",
   "foto": true
 },
 {
   "id": 2,
   "ordem": "Columbiformes",
   "familia": "Columbidae",
   "nomeCientifico": "Patagioenas picazuro",
   "nomeComumBrasileiro": "pomba-asa-branca",
   "descricao": "Temminck, 1813",
   "nomeComumIngles": "Picazuro Pigeon",
   "periodoAtividade": "Diurno",
   "dimorfismo": "Não",
   "estadoConservacaoIucn": "Pouco Preocupante",
   "endemicaBrasil": "Não",
   "habitats": "Florestas e matas (úmidas, secas, ciliares etc.), Campos e pastagens, Bordas de mata, Áreas rurais, Áreas urbanas",
   "dieta": "Sementes, Frutos",
   "particula": "pomba-asa-branca",
   "foto": true
 },
 {
   "id": 3,
   "ordem": "Columbiformes",
   "familia": "Columbidae",
   "nomeCientifico": "Zenaida auriculata",
   "nomeComumBrasileiro": "avoante",
   "descricao": "Des Murs, 1847",
   "nomeComumIngles": "Eared Dove",
   "periodoAtividade": "Diurno",
   "dimorfismo": "Não",
   "estadoConservacaoIucn": "Pouco Preocupante",
   "endemicaBrasil": "Não",
   "habitats": "Campos e pastagens, Cerrado e vegetação de savana, Ambientes antrópicos (plantios, jardins, construções), Bordas de mata, Áreas urbanas",
   "dieta": "Sementes, Frutos",
   "particula": "avoante",
   "foto": true
 },
 {
   "id": 4,
   "ordem": "Columbiformes",
   "familia": "Columbidae",
   "nomeCientifico": "Columbina talpacoti",
   "nomeComumBrasileiro": "rolinha-roxa",
   "descricao": "Temminck, 1811",
   "nomeComumIngles": "Ruddy Ground-Dove",
   "periodoAtividade": "Diurno",
   "dimorfismo": "Sim",
   "estadoConservacaoIucn": "Pouco Preocupante",
   "endemicaBrasil": "Não",
   "habitats": "Áreas urbanas, Ambientes antrópicos (plantios, jardins, construções), Áreas abertas, Campos e pastagens, Bordas de mata",
   "dieta": "Sementes, Frutos",
   "particula": "rolinha-roxa",
   "foto": true
 },
 {
   "id": 5,
   "ordem": "Columbiformes",
   "familia": "Columbidae",
   "nomeCientifico": "Columbina squammata",
   "nomeComumBrasileiro": "rolinha-fogo-apagou",
   "descricao": "Lesson, 1831",
   "nomeComumIngles": "Scaled Dove",
   "periodoAtividade": "Diurno",
   "dimorfismo": "Não",
   "estadoConservacaoIucn": "Pouco Preocupante",
   "endemicaBrasil": "Não",
   "habitats": "Cerrado e vegetação de savana, Campos e pastagens, Áreas rurais",
   "dieta": "Sementes, Frutos",
   "particula": "rolinha-fogo-apagou",
   "foto": true
 },
 {
   "id": 6,
   "ordem": "Cuculiformes",
   "familia": "Cuculidae",
   "nomeCientifico": "Guira guira",
   "nomeComumBrasileiro": "anu-branco",
   "descricao": "Gmelin, 1788",
   "nomeComumIngles": "Guira Cuckoo",
   "periodoAtividade": "Diurno",
   "dimorfismo": "Não",
   "estadoConservacaoIucn": "Pouco Preocupante",
   "endemicaBrasil": "Não",
   "habitats": "Áreas abertas, Campos e pastagens, Cerrado e vegetação de savana, Bordas de mata, Áreas urbanas",
   "dieta": "Artrópodes, Pequenos vertebrados",
   "particula": "anu-branco",
   "foto": true
 },
 {
   "id": 7,
   "ordem": "Cuculiformes",
   "familia": "Cuculidae",
   "nomeCientifico": "Crotophaga ani",
   "nomeComumBrasileiro": "anu-preto",
   "descricao": "Linnaeus, 1758",
   "nomeComumIngles": "Smooth-billed Ani",
   "periodoAtividade": "Diurno",
   "dimorfismo": "Não",
   "estadoConservacaoIucn": "Pouco Preocupante",
   "endemicaBrasil": "Não",
   "habitats": "Áreas abertas, Campos e pastagens, Bordas de mata, Áreas rurais, Áreas urbanas",
   "dieta": "Artrópodes, Pequenos vertebrados",
   "particula": "anu-preto",
   "foto": true
 },
 {
   "id": 8,
   "ordem": "Cuculiformes",
   "familia": "Cuculidae",
   "nomeCientifico": "Piaya cayana",
   "nomeComumBrasileiro": "alma-de-gato",
   "descricao": "Linnaeus, 1766",
   "nomeComumIngles": "Squirrel Cuckoo",
   "periodoAtividade": "Diurno",
   "dimorfismo": "Não",
   "estadoConservacaoIucn": "Pouco Preocupante",
   "endemicaBrasil": "Não",
   "habitats": "Florestas e matas (úmidas, secas, ciliares etc.), Cerrado e vegetação de savana, Bordas de mata",
   "dieta": "Artrópodes, Pequenos vertebrados",
   "particula": "alma-de-gato",
   "foto": true
 },
 {
   "id": 9,
   "ordem": "Nyctibiiformes",
   "familia": "Nyctibiidae",
   "nomeCientifico": "Nyctibius griseus",
   "nomeComumBrasileiro": "urutau",
   "descricao": "Gmelin, 1789",
   "nomeComumIngles": "Common Potoo",
   "periodoAtividade": "Noturno",
   "dimorfismo": "Não",
   "estadoConservacaoIucn": "Pouco Preocupante",
   "endemicaBrasil": "Não",
   "habitats": "Florestas e matas (úmidas, secas, ciliares etc.), Cerrado e vegetação de savana",
   "dieta": "Artrópodes",
   "particula": "urutau",
   "foto": true
 },
 {
   "id": 10,
   "ordem": "Caprimulgiformes",
   "familia": "Caprimulgidae",
   "nomeCientifico": "Chordeiles nacunda",
   "nomeComumBrasileiro": "corucão",
   "descricao": "Vieillot, 1817",
   "nomeComumIngles": "Nacunda Nighthawk",
   "periodoAtividade": "Noturno",
   "dimorfismo": "Não",
   "estadoConservacaoIucn": "Pouco Preocupante",
   "endemicaBrasil": "Não",
   "habitats": "Campos e pastagens, Ambientes antrópicos (plantios, jardins, construções), Cerrado e vegetação de savana",
   "dieta": "Artrópodes",
   "particula": "corucao",
   "foto": true
 },
 {
   "id": 11,
   "ordem": "Apodiformes",
   "familia": "Apodidae",
   "nomeCientifico": "Chaetura meridionalis",
   "nomeComumBrasileiro": "andorinhão-do-temporal",
   "descricao": "Hellmayr, 1907",
   "nomeComumIngles": "Sick's Swift",
   "periodoAtividade": "Diurno",
   "dimorfismo": "Não",
   "estadoConservacaoIucn": "Pouco Preocupante",
   "endemicaBrasil": "Não",
   "habitats": "Áreas urbanas, Florestas e matas (úmidas, secas, ciliares etc.), Bordas de mata, Áreas rurais",
   "dieta": "Artrópodes",
   "particula": "andorinhao-do-temporal",
   "foto": true
 },
 {
   "id": 12,
   "ordem": "Apodiformes",
   "familia": "Apodidae",
   "nomeCientifico": "Tachornis squamata",
   "nomeComumBrasileiro": "andorinhão-do-buriti",
   "descricao": "Cassin, 1853",
   "nomeComumIngles": "Fork-tailed Palm-Swift",
   "periodoAtividade": "Diurno",
   "dimorfismo": "Não",
   "estadoConservacaoIucn": "Pouco Preocupante",
   "endemicaBrasil": "Não",
   "habitats": "Florestas e matas (úmidas, secas, ciliares etc.), Cerrado e vegetação de savana",
   "dieta": "Artrópodes",
   "particula": "andorinhao-do-buriti",
   "foto": true
 },
 {
   "id": 13,
   "ordem": "Apodiformes",
   "familia": "Trochilidae",
   "nomeCientifico": "Heliomaster squamosus",
   "nomeComumBrasileiro": "bico-reto-de-banda-branca",
   "descricao": "Temminck, 1823",
   "nomeComumIngles": "Stripe-breasted Starthroat",
   "periodoAtividade": "Diurno",
   "dimorfismo": "Sim",
   "estadoConservacaoIucn": "Pouco Preocupante",
   "endemicaBrasil": "Sim",
   "habitats": "Florestas e matas (úmidas, secas, ciliares etc.), Cerrado e vegetação de savana, Ambientes antrópicos (plantios, jardins, construções)",
   "dieta": "Néctar, Artrópodes",
   "particula": "bico-reto-de-banda-branca",
   "foto": true
 },
 {
   "id": 14,
   "ordem": "Apodiformes",
   "familia": "Trochilidae",
   "nomeCientifico": "Chlorostilbon lucidus",
   "nomeComumBrasileiro": "besourinho-de-bico-vermelho",
   "descricao": "Shaw, 1812",
   "nomeComumIngles": "Glittering-bellied Emerald",
   "periodoAtividade": "Diurno",
   "dimorfismo": "Sim",
   "estadoConservacaoIucn": "Pouco Preocupante",
   "endemicaBrasil": "Não",
   "habitats": "Florestas e matas (úmidas, secas, ciliares etc.), Cerrado e vegetação de savana, Áreas urbanas",
   "dieta": "Néctar, Artrópodes",
   "particula": "besourinho-de-bico-vermelho",
   "foto": true
 },
 {
   "id": 15,
   "ordem": "Apodiformes",
   "familia": "Trochilidae",
   "nomeCientifico": "Eupetomena macroura",
   "nomeComumBrasileiro": "beija-flor-tesoura",
   "descricao": "Gmelin, 1788",
   "nomeComumIngles": "Swallow-tailed Hummingbird",
   "periodoAtividade": "Diurno",
   "dimorfismo": "Não",
   "estadoConservacaoIucn": "Pouco Preocupante",
   "endemicaBrasil": "Não",
   "habitats": "Florestas e matas (úmidas, secas, ciliares etc.), Cerrado e vegetação de savana, Áreas urbanas",
   "dieta": "Néctar, Artrópodes",
   "particula": "beija-flor-tesoura",
   "foto": true
 },
 {
   "id": 16,
   "ordem": "Apodiformes",
   "familia": "Trochilidae",
   "nomeCientifico": "Chrysuronia versicolor",
   "nomeComumBrasileiro": "beija-flor-de-banda-branca",
   "descricao": "Vieillot, 1818",
   "nomeComumIngles": "Versicolored Emerald",
   "periodoAtividade": "Diurno",
   "dimorfismo": "Não",
   "estadoConservacaoIucn": "Pouco Preocupante",
   "endemicaBrasil": "Não",
   "habitats": "Florestas e matas (úmidas, secas, ciliares etc.), Cerrado e vegetação de savana, Áreas urbanas",
   "dieta": "Néctar, Artrópodes",
   "particula": "beija-flor-de-banda-branca",
   "foto": true
 },
 {
   "id": 17,
   "ordem": "Apodiformes",
   "familia": "Trochilidae",
   "nomeCientifico": "Chionomesa fimbriata",
   "nomeComumBrasileiro": "beija-flor-de-garganta-verde",
   "descricao": "Gmelin, 1788",
   "nomeComumIngles": "Glittering-throated Emerald",
   "periodoAtividade": "Diurno",
   "dimorfismo": "Não",
   "estadoConservacaoIucn": "Pouco Preocupante",
   "endemicaBrasil": "Não",
   "habitats": "Florestas e matas (úmidas, secas, ciliares etc.), Cerrado e vegetação de savana, Áreas urbanas",
   "dieta": "Néctar, Artrópodes",
   "particula": "beija-flor-de-garganta-verde",
   "foto": true
 },
 {
   "id": 18,
   "ordem": "Apodiformes",
   "familia": "Trochilidae",
   "nomeCientifico": "Chionomesa lactea",
   "nomeComumBrasileiro": "beija-flor-de-peito-azul",
   "descricao": "Lesson, 1832",
   "nomeComumIngles": "Sapphire-spangled Emerald",
   "periodoAtividade": "Diurno",
   "dimorfismo": "Não",
   "estadoConservacaoIucn": "Pouco Preocupante",
   "endemicaBrasil": "Não",
   "habitats": "Florestas e matas (úmidas, secas, ciliares etc.), Cerrado e vegetação de savana, Áreas urbanas",
   "dieta": "Néctar, Artrópodes",
   "particula": "beija-flor-de-peito-azul",
   "foto": true
 },
 {
   "id": 19,
   "ordem": "Charadriiformes",
   "familia": "Charadriidae",
   "nomeCientifico": "Vanellus chilensis",
   "nomeComumBrasileiro": "quero-quero",
   "descricao": "Molina, 1782",
   "nomeComumIngles": "Southern Lapwing",
   "periodoAtividade": "Diurno, Noturno",
   "dimorfismo": "Não",
   "estadoConservacaoIucn": "Pouco Preocupante",
   "endemicaBrasil": "Não",
   "habitats": "Campos e pastagens, Ambientes antrópicos (plantios, jardins, construções), Áreas urbanas",
   "dieta": "Artrópodes, Vermes",
   "particula": "quero-quero",
   "foto": true
 },
 {
   "id": 20,
   "ordem": "Pelecaniformes",
   "familia": "Ardeidae",
   "nomeCientifico": "Ardea ibis",
   "nomeComumBrasileiro": "garça-vaqueira",
   "descricao": "Linnaeus, 1758",
   "nomeComumIngles": "Cattle Egret",
   "periodoAtividade": "Diurno",
   "dimorfismo": "Não",
   "estadoConservacaoIucn": "Pouco Preocupante",
   "endemicaBrasil": "Não",
   "habitats": "Ambientes aquáticos e úmidos, Campos e pastagens",
   "dieta": "Peixes, Artrópodes, Pequenos vertebrados",
   "particula": "garca-vaqueira",
   "foto": true
 },
 {
   "id": 21,
   "ordem": "Pelecaniformes",
   "familia": "Ardeidae",
   "nomeCientifico": "Syrigma sibilatrix",
   "nomeComumBrasileiro": "maria-faceira",
   "descricao": "Temminck, 1824",
   "nomeComumIngles": "Whistling Heron",
   "periodoAtividade": "Diurno",
   "dimorfismo": "Não",
   "estadoConservacaoIucn": "Pouco Preocupante",
   "endemicaBrasil": "Não",
   "habitats": "Ambientes aquáticos e úmidos, Campos e pastagens",
   "dieta": "Peixes, Artrópodes, Pequenos vertebrados",
   "particula": "maria-faceira",
   "foto": true
 },
 {
   "id": 22,
   "ordem": "Pelecaniformes",
   "familia": "Ardeidae",
   "nomeCientifico": "Egretta thula",
   "nomeComumBrasileiro": "garça-branca-pequena",
   "descricao": "Molina, 1782",
   "nomeComumIngles": "Snowy Egret",
   "periodoAtividade": "Diurno",
   "dimorfismo": "Não",
   "estadoConservacaoIucn": "Pouco Preocupante",
   "endemicaBrasil": "Não",
   "habitats": "Ambientes aquáticos e úmidos, Campos e pastagens",
   "dieta": "Peixes, Artrópodes, Pequenos vertebrados",
   "particula": "garca-branca-pequena",
   "foto": true
 },
 {
   "id": 23,
   "ordem": "Pelecaniformes",
   "familia": "Threskiornithidae",
   "nomeCientifico": "Mesembrinibis cayennensis",
   "nomeComumBrasileiro": "coró-coró",
   "descricao": "Gmelin, 1789",
   "nomeComumIngles": "Green Ibis",
   "periodoAtividade": "Diurno",
   "dimorfismo": "Não",
   "estadoConservacaoIucn": "Pouco Preocupante",
   "endemicaBrasil": "Não",
   "habitats": "Ambientes aquáticos e úmidos, Florestas e matas (úmidas, secas, ciliares etc.)",
   "dieta": "Artrópodes, Vermes",
   "particula": "coro-coro",
   "foto": true
 },
 {
   "id": 24,
   "ordem": "Pelecaniformes",
   "familia": "Threskiornithidae",
   "nomeCientifico": "Phimosus infuscatus",
   "nomeComumBrasileiro": "tapicuru",
   "descricao": "Lichtenstein, 1823",
   "nomeComumIngles": "Bare-faced Ibis",
   "periodoAtividade": "Diurno",
   "dimorfismo": "Não",
   "estadoConservacaoIucn": "Pouco Preocupante",
   "endemicaBrasil": "Não",
   "habitats": "Ambientes aquáticos e úmidos, Campos e pastagens",
   "dieta": "Artrópodes, Vermes",
   "particula": "tapicuru",
   "foto": true
 },
 {
   "id": 25,
   "ordem": "Pelecaniformes",
   "familia": "Threskiornithidae",
   "nomeCientifico": "Theristicus caudatus",
   "nomeComumBrasileiro": "curicaca",
   "descricao": "Boddaert, 1783",
   "nomeComumIngles": "Buff-necked Ibis",
   "periodoAtividade": "Diurno",
   "dimorfismo": "Não",
   "estadoConservacaoIucn": "Pouco Preocupante",
   "endemicaBrasil": "Não",
   "habitats": "Ambientes aquáticos e úmidos, Campos e pastagens",
   "dieta": "Artrópodes, Vermes",
   "particula": "curicaca",
   "foto": true
 },
 {
   "id": 26,
   "ordem": "Cathartiformes",
   "familia": "Cathartidae",
   "nomeCientifico": "Coragyps atratus",
   "nomeComumBrasileiro": "urubu-preto",
   "descricao": "Bechstein, 1793",
   "nomeComumIngles": "Black Vulture",
   "periodoAtividade": "Diurno",
   "dimorfismo": "Não",
   "estadoConservacaoIucn": "Pouco Preocupante",
   "endemicaBrasil": "Não",
   "habitats": "Áreas urbanas, Áreas rurais, Campos e pastagens, Florestas e matas (úmidas, secas, ciliares etc.)",
   "dieta": "Carcaças de animais mortos",
   "particula": "urubu-preto",
   "foto": true
 },
 {
   "id": 27,
   "ordem": "Accipitriformes",
   "familia": "Accipitridae",
   "nomeCientifico": "Ictinia plumbea",
   "nomeComumBrasileiro": "sovi",
   "descricao": "Gmelin, 1788",
   "nomeComumIngles": "Plumbeous Kite",
   "periodoAtividade": "Diurno",
   "dimorfismo": "Não",
   "estadoConservacaoIucn": "Pouco Preocupante",
   "endemicaBrasil": "Não",
   "habitats": "Florestas e matas (úmidas, secas, ciliares etc.), Cerrado e vegetação de savana, Áreas urbanas",
   "dieta": "Artrópodes, Pequenos vertebrados",
   "particula": "sovi",
   "foto": true
 },
 {
   "id": 28,
   "ordem": "Accipitriformes",
   "familia": "Accipitridae",
   "nomeCientifico": "Geranospiza caerulescens",
   "nomeComumBrasileiro": "gavião-pernilongo",
   "descricao": "Vieillot, 1817",
   "nomeComumIngles": "Crane Hawk",
   "periodoAtividade": "Diurno",
   "dimorfismo": "Não",
   "estadoConservacaoIucn": "Pouco Preocupante",
   "endemicaBrasil": "Não",
   "habitats": "Florestas e matas (úmidas, secas, ciliares etc.), Cerrado e vegetação de savana, Áreas urbanas",
   "dieta": "Artrópodes, Pequenos vertebrados",
   "particula": "gaviao-pernilongo",
   "foto": true
 },
 {
   "id": 29,
   "ordem": "Accipitriformes",
   "familia": "Accipitridae",
   "nomeCientifico": "Rupornis magnirostris",
   "nomeComumBrasileiro": "gavião-carijó",
   "descricao": "Gmelin, 1788",
   "nomeComumIngles": "Roadside Hawk",
   "periodoAtividade": "Diurno",
   "dimorfismo": "Não",
   "estadoConservacaoIucn": "Pouco Preocupante",
   "endemicaBrasil": "Não",
   "habitats": "Florestas e matas (úmidas, secas, ciliares etc.), Cerrado e vegetação de savana, Áreas urbanas",
   "dieta": "Artrópodes, Pequenos vertebrados",
   "particula": "gaviao-carijo",
   "foto": true
 },
 {
   "id": 30,
   "ordem": "Accipitriformes",
   "familia": "Accipitridae",
   "nomeCientifico": "Geranoaetus albicaudatus",
   "nomeComumBrasileiro": "gavião-de-rabo-branco",
   "descricao": "Vieillot, 1816",
   "nomeComumIngles": "White-tailed Hawk",
   "periodoAtividade": "Diurno",
   "dimorfismo": "Não",
   "estadoConservacaoIucn": "Pouco Preocupante",
   "endemicaBrasil": "Não",
   "habitats": "Campos e pastagens, Ambientes antrópicos (plantios, jardins, construções), Cerrado e vegetação de savana",
   "dieta": "Pequenos mamíferos, Pequenos vertebrados",
   "particula": "gaviao-de-rabo-branco",
   "foto": true
 },
 {
   "id": 31,
   "ordem": "Accipitriformes",
   "familia": "Accipitridae",
   "nomeCientifico": "Buteo brachyurus",
   "nomeComumBrasileiro": "gavião-de-cauda-curta",
   "descricao": "Vieillot, 1816",
   "nomeComumIngles": "Short-tailed Hawk",
   "periodoAtividade": "Diurno",
   "dimorfismo": "Não",
   "estadoConservacaoIucn": "Pouco Preocupante",
   "endemicaBrasil": "Não",
   "habitats": "Florestas e matas (úmidas, secas, ciliares etc.), Cerrado e vegetação de savana, Áreas urbanas",
   "dieta": "Pequenos mamíferos, Pequenos vertebrados",
   "particula": "gaviao-de-cauda-curta",
   "foto": true
 },
 {
   "id": 32,
   "ordem": "Strigiformes",
   "familia": "Strigidae",
   "nomeCientifico": "Megascops choliba",
   "nomeComumBrasileiro": "corujinha-do-mato",
   "descricao": "Vieillot, 1817",
   "nomeComumIngles": "Tropical Screech-Owl",
   "periodoAtividade": "Noturno",
   "dimorfismo": "Não",
   "estadoConservacaoIucn": "Pouco Preocupante",
   "endemicaBrasil": "Não",
   "habitats": "Florestas e matas (úmidas, secas, ciliares etc.), Cerrado e vegetação de savana, Áreas urbanas",
   "dieta": "Artrópodes, Pequenos vertebrados",
   "particula": "corujinha-do-mato",
   "foto": true
 },
 {
   "id": 33,
   "ordem": "Strigiformes",
   "familia": "Strigidae",
   "nomeCientifico": "Athene cunicularia",
   "nomeComumBrasileiro": "coruja-buraqueira",
   "descricao": "Molina, 1782",
   "nomeComumIngles": "Burrowing Owl",
   "periodoAtividade": "Diurno, Noturno",
   "dimorfismo": "Não",
   "estadoConservacaoIucn": "Pouco Preocupante",
   "endemicaBrasil": "Não",
   "habitats": "Campos e pastagens, Ambientes antrópicos (plantios, jardins, construções), Áreas urbanas",
   "dieta": "Artrópodes, Pequenos vertebrados",
   "particula": "coruja-buraqueira",
   "foto": true
 },
 {
   "id": 34,
   "ordem": "Coraciiformes",
   "familia": "Alcedinidae",
   "nomeCientifico": "Megaceryle torquata",
   "nomeComumBrasileiro": "martim-pescador-grande",
   "descricao": "Linnaeus, 1766",
   "nomeComumIngles": "Ringed Kingfisher",
   "periodoAtividade": "Diurno",
   "dimorfismo": "Sim",
   "estadoConservacaoIucn": "Pouco Preocupante",
   "endemicaBrasil": "Não",
   "habitats": "Ambientes aquáticos e úmidos",
   "dieta": "Peixes, Artrópodes",
   "particula": "martim-pescador-grande",
   "foto": true
 },
 {
   "id": 35,
   "ordem": "Piciformes",
   "familia": "Ramphastidae",
   "nomeCientifico": "Ramphastos toco",
   "nomeComumBrasileiro": "tucanuçu",
   "descricao": "Statius Muller, 1776",
   "nomeComumIngles": "Toco Toucan",
   "periodoAtividade": "Diurno",
   "dimorfismo": "Não",
   "estadoConservacaoIucn": "Pouco Preocupante",
   "endemicaBrasil": "Não",
   "habitats": "Florestas e matas (úmidas, secas, ciliares etc.), Cerrado e vegetação de savana, Áreas urbanas",
   "dieta": "Frutos, Artrópodes, Pequenos vertebrados",
   "particula": "tucanucu",
   "foto": true
 },
 {
   "id": 36,
   "ordem": "Piciformes",
   "familia": "Picidae",
   "nomeCientifico": "Picumnus albosquamatus",
   "nomeComumBrasileiro": "picapauzinho-escamoso",
   "descricao": "d'Orbigny, 1840",
   "nomeComumIngles": "White-wedged Piculet",
   "periodoAtividade": "Diurno",
   "dimorfismo": "Sim",
   "estadoConservacaoIucn": "Pouco Preocupante",
   "endemicaBrasil": "Não",
   "habitats": "Florestas e matas (úmidas, secas, ciliares etc.), Cerrado e vegetação de savana, Áreas urbanas",
   "dieta": "Artrópodes",
   "particula": "picapauzinho-escamoso",
   "foto": true
 },
 {
   "id": 37,
   "ordem": "Piciformes",
   "familia": "Picidae",
   "nomeCientifico": "Melanerpes candidus",
   "nomeComumBrasileiro": "pica-pau-branco",
   "descricao": "Otto, 1796",
   "nomeComumIngles": "White Woodpecker",
   "periodoAtividade": "Diurno",
   "dimorfismo": "Não",
   "estadoConservacaoIucn": "Pouco Preocupante",
   "endemicaBrasil": "Não",
   "habitats": "Florestas e matas (úmidas, secas, ciliares etc.), Cerrado e vegetação de savana, Áreas urbanas",
   "dieta": "Artrópodes, Frutos",
   "particula": "pica-pau-branco",
   "foto": true
 },
 {
   "id": 38,
   "ordem": "Piciformes",
   "familia": "Picidae",
   "nomeCientifico": "Dryobates passerinus",
   "nomeComumBrasileiro": "pica-pau-pequeno",
   "descricao": "Linnaeus, 1766",
   "nomeComumIngles": "Little Woodpecker",
   "periodoAtividade": "Diurno",
   "dimorfismo": "Sim",
   "estadoConservacaoIucn": "Pouco Preocupante",
   "endemicaBrasil": "Não",
   "habitats": "Florestas e matas (úmidas, secas, ciliares etc.), Cerrado e vegetação de savana, Áreas urbanas",
   "dieta": "Artrópodes",
   "particula": "pica-pau-pequeno",
   "foto": true
 },
 {
   "id": 39,
   "ordem": "Piciformes",
   "familia": "Picidae",
   "nomeCientifico": "Colaptes melanochloros",
   "nomeComumBrasileiro": "pica-pau-verde-barrado",
   "descricao": "Gmelin, 1788",
   "nomeComumIngles": "Green-barred Woodpecker",
   "periodoAtividade": "Diurno",
   "dimorfismo": "Sim",
   "estadoConservacaoIucn": "Pouco Preocupante",
   "endemicaBrasil": "Não",
   "habitats": "Florestas e matas (úmidas, secas, ciliares etc.), Cerrado e vegetação de savana, Áreas urbanas",
   "dieta": "Artrópodes, Frutos",
   "particula": "pica-pau-verde-barrado",
   "foto": true
 },
 {
   "id": 40,
   "ordem": "Piciformes",
   "familia": "Picidae",
   "nomeCientifico": "Colaptes campestris",
   "nomeComumBrasileiro": "pica-pau-do-campo",
   "descricao": "Vieillot, 1818",
   "nomeComumIngles": "Campo Flicker",
   "periodoAtividade": "Diurno",
   "dimorfismo": "Não",
   "estadoConservacaoIucn": "Pouco Preocupante",
   "endemicaBrasil": "Não",
   "habitats": "Campos e pastagens, Ambientes antrópicos (plantios, jardins, construções), Cerrado e vegetação de savana",
   "dieta": "Artrópodes, Frutos",
   "particula": "pica-pau-do-campo",
   "foto": true
 },
 {
   "id": 41,
   "ordem": "Cariamiformes",
   "familia": "Cariamidae",
   "nomeCientifico": "Cariama cristata",
   "nomeComumBrasileiro": "seriema",
   "descricao": "Linnaeus, 1766",
   "nomeComumIngles": "Red-legged Seriema",
   "periodoAtividade": "Diurno",
   "dimorfismo": "Não",
   "estadoConservacaoIucn": "Pouco Preocupante",
   "endemicaBrasil": "Não",
   "habitats": "Campos e pastagens, Ambientes antrópicos (plantios, jardins, construções), Cerrado e vegetação de savana",
   "dieta": "Artrópodes, Pequenos vertebrados",
   "particula": "seriema",
   "foto": true
 },
 {
   "id": 42,
   "ordem": "Falconiformes",
   "familia": "Falconidae",
   "nomeCientifico": "Caracara plancus",
   "nomeComumBrasileiro": "carcará",
   "descricao": "Miller, 1777",
   "nomeComumIngles": "Crested Caracara",
   "periodoAtividade": "Diurno",
   "dimorfismo": "Não",
   "estadoConservacaoIucn": "Pouco Preocupante",
   "endemicaBrasil": "Não",
   "habitats": "Campos e pastagens, Ambientes antrópicos (plantios, jardins, construções), Áreas urbanas",
   "dieta": "Carcaças de animais mortos, Artrópodes, Pequenos vertebrados",
   "particula": "carcara",
   "foto": true
 },
 {
   "id": 43,
   "ordem": "Psittaciformes",
   "familia": "Psittacidae",
   "nomeCientifico": "Brotogeris chiriri",
   "nomeComumBrasileiro": "periquito-de-encontro-amarelo",
   "descricao": "Vieillot, 1818",
   "nomeComumIngles": "Yellow-chevroned Parakeet",
   "periodoAtividade": "Diurno",
   "dimorfismo": "Não",
   "estadoConservacaoIucn": "Pouco Preocupante",
   "endemicaBrasil": "Não",
   "habitats": "Florestas e matas (úmidas, secas, ciliares etc.), Cerrado e vegetação de savana, Áreas urbanas",
   "dieta": "Frutos, Sementes",
   "particula": "periquito-de-encontro-amarelo",
   "foto": true
 },
 {
   "id": 44,
   "ordem": "Psittaciformes",
   "familia": "Psittacidae",
   "nomeCientifico": "Amazona aestiva",
   "nomeComumBrasileiro": "papagaio-verdadeiro",
   "descricao": "Linnaeus, 1758",
   "nomeComumIngles": "Turquoise-fronted Parrot",
   "periodoAtividade": "Diurno",
   "dimorfismo": "Não",
   "estadoConservacaoIucn": "Pouco Preocupante",
   "endemicaBrasil": "Não",
   "habitats": "Florestas e matas (úmidas, secas, ciliares etc.), Cerrado e vegetação de savana, Áreas urbanas",
   "dieta": "Frutos, Sementes",
   "particula": "papagaio-verdadeiro",
   "foto": true
 },
 {
   "id": 45,
   "ordem": "Psittaciformes",
   "familia": "Psittacidae",
   "nomeCientifico": "Amazona amazonica",
   "nomeComumBrasileiro": "curica",
   "descricao": "Linnaeus, 1766",
   "nomeComumIngles": "Orange-winged Parrot",
   "periodoAtividade": "Diurno",
   "dimorfismo": "Não",
   "estadoConservacaoIucn": "Pouco Preocupante",
   "endemicaBrasil": "Não",
   "habitats": "Florestas e matas (úmidas, secas, ciliares etc.), Cerrado e vegetação de savana, Áreas urbanas",
   "dieta": "Frutos, Sementes",
   "particula": "curica",
   "foto": true
 },
 {
   "id": 46,
   "ordem": "Psittaciformes",
   "familia": "Psittacidae",
   "nomeCientifico": "Forpus xanthopterygius",
   "nomeComumBrasileiro": "tuim",
   "descricao": "Spix, 1824",
   "nomeComumIngles": "Blue-winged Parrotlet",
   "periodoAtividade": "Diurno",
   "dimorfismo": "Sim",
   "estadoConservacaoIucn": "Pouco Preocupante",
   "endemicaBrasil": "Não",
   "habitats": "Florestas e matas (úmidas, secas, ciliares etc.), Cerrado e vegetação de savana, Áreas urbanas",
   "dieta": "Frutos, Sementes",
   "particula": "tuim",
   "foto": true
 },
 {
   "id": 47,
   "ordem": "Psittaciformes",
   "familia": "Psittacidae",
   "nomeCientifico": "Eupsittula aurea",
   "nomeComumBrasileiro": "periquito-rei",
   "descricao": "Gmelin, 1788",
   "nomeComumIngles": "Peach-fronted Parakeet",
   "periodoAtividade": "Diurno",
   "dimorfismo": "Não",
   "estadoConservacaoIucn": "Pouco Preocupante",
   "endemicaBrasil": "Não",
   "habitats": "Florestas e matas (úmidas, secas, ciliares etc.), Cerrado e vegetação de savana, Áreas urbanas",
   "dieta": "Frutos, Sementes",
   "particula": "periquito-rei",
   "foto": true
 },
 {
   "id": 48,
   "ordem": "Psittaciformes",
   "familia": "Psittacidae",
   "nomeCientifico": "Psittacara leucophthalmus",
   "nomeComumBrasileiro": "periquitão",
   "descricao": "Statius Muller, 1776",
   "nomeComumIngles": "White-eyed Parakeet",
   "periodoAtividade": "Diurno",
   "dimorfismo": "Não",
   "estadoConservacaoIucn": "Pouco Preocupante",
   "endemicaBrasil": "Não",
   "habitats": "Florestas e matas (úmidas, secas, ciliares etc.), Cerrado e vegetação de savana, Áreas urbanas",
   "dieta": "Frutos, Sementes",
   "particula": "periquitao",
   "foto": true
 },
 {
   "id": 49,
   "ordem": "Passeriformes",
   "familia": "Thamnophilidae",
   "nomeCientifico": "Herpsilochmus longirostris",
   "nomeComumBrasileiro": "chorozinho-de-bico-comprido",
   "descricao": "Pelzeln, 1868",
   "nomeComumIngles": "Large-billed Antwren",
   "periodoAtividade": "Diurno",
   "dimorfismo": "Sim",
   "estadoConservacaoIucn": "Pouco Preocupante",
   "endemicaBrasil": "Não",
   "habitats": "Florestas e matas (úmidas, secas, ciliares etc.), Cerrado e vegetação de savana",
   "dieta": "Artrópodes",
   "particula": "chorozinho-de-bico-comprido",
   "foto": true
 },
 {
   "id": 50,
   "ordem": "Passeriformes",
   "familia": "Thamnophilidae",
   "nomeCientifico": "Herpsilochmus atricapillus",
   "nomeComumBrasileiro": "chorozinho-de-chapéu-preto",
   "descricao": "Pelzeln, 1868",
   "nomeComumIngles": "Black-capped Antwren",
   "periodoAtividade": "Diurno",
   "dimorfismo": "Sim",
   "estadoConservacaoIucn": "Pouco Preocupante",
   "endemicaBrasil": "Não",
   "habitats": "Florestas e matas (úmidas, secas, ciliares etc.), Cerrado e vegetação de savana",
   "dieta": "Artrópodes",
   "particula": "chorozinho-de-chapeu-preto",
   "foto": true
 },
 {
   "id": 51,
   "ordem": "Passeriformes",
   "familia": "Thamnophilidae",
   "nomeCientifico": "Thamnophilus doliatus",
   "nomeComumBrasileiro": "choca-barrada",
   "descricao": "Linnaeus, 1764",
   "nomeComumIngles": "Barred Antshrike",
   "periodoAtividade": "Diurno",
   "dimorfismo": "Sim",
   "estadoConservacaoIucn": "Pouco Preocupante",
   "endemicaBrasil": "Não",
   "habitats": "Florestas e matas (úmidas, secas, ciliares etc.), Cerrado e vegetação de savana",
   "dieta": "Artrópodes",
   "particula": "choca-barrada",
   "foto": true
 },
 {
   "id": 52,
   "ordem": "Passeriformes",
   "familia": "Dendrocolaptidae",
   "nomeCientifico": "Lepidocolaptes angustirostris",
   "nomeComumBrasileiro": "arapaçu-de-cerrado",
   "descricao": "Vieillot, 1818",
   "nomeComumIngles": "Narrow-billed Woodcreeper",
   "periodoAtividade": "Diurno",
   "dimorfismo": "Não",
   "estadoConservacaoIucn": "Pouco Preocupante",
   "endemicaBrasil": "Não",
   "habitats": "Florestas e matas (úmidas, secas, ciliares etc.), Cerrado e vegetação de savana",
   "dieta": "Artrópodes",
   "particula": "arapacu-de-cerrado",
   "foto": true
 },
 {
   "id": 53,
   "ordem": "Passeriformes",
   "familia": "Furnariidae",
   "nomeCientifico": "Furnarius rufus",
   "nomeComumBrasileiro": "joão-de-barro",
   "descricao": "Gmelin, 1788",
   "nomeComumIngles": "Rufous Hornero",
   "periodoAtividade": "Diurno",
   "dimorfismo": "Não",
   "estadoConservacaoIucn": "Pouco Preocupante",
   "endemicaBrasil": "Não",
   "habitats": "Campos e pastagens, Ambientes antrópicos (plantios, jardins, construções), Áreas urbanas",
   "dieta": "Artrópodes",
   "particula": "joao-de-barro",
   "foto": true
 },
 {
   "id": 54,
   "ordem": "Passeriformes",
   "familia": "Furnariidae",
   "nomeCientifico": "Synallaxis frontalis",
   "nomeComumBrasileiro": "petrim",
   "descricao": "Pelzeln, 1859",
   "nomeComumIngles": "Sooty-fronted Spinetail",
   "periodoAtividade": "Diurno",
   "dimorfismo": "Não",
   "estadoConservacaoIucn": "Pouco Preocupante",
   "endemicaBrasil": "Não",
   "habitats": "Florestas e matas (úmidas, secas, ciliares etc.), Cerrado e vegetação de savana",
   "dieta": "Artrópodes",
   "particula": "petrim",
   "foto": true
 },
 {
   "id": 55,
   "ordem": "Passeriformes",
   "familia": "Rhynchocyclidae",
   "nomeCientifico": "Todirostrum cinereum",
   "nomeComumBrasileiro": "ferreirinho-relógio",
   "descricao": "Linnaeus, 1766",
   "nomeComumIngles": "Common Tody-Flycatcher",
   "periodoAtividade": "Diurno",
   "dimorfismo": "Não",
   "estadoConservacaoIucn": "Pouco Preocupante",
   "endemicaBrasil": "Não",
   "habitats": "Florestas e matas (úmidas, secas, ciliares etc.), Cerrado e vegetação de savana",
   "dieta": "Artrópodes",
   "particula": "ferreirinho-relogio",
   "foto": true
 },
 {
   "id": 56,
   "ordem": "Passeriformes",
   "familia": "Tyrannidae",
   "nomeCientifico": "Hirundinea ferruginea",
   "nomeComumBrasileiro": "gibão-de-couro",
   "descricao": "Gmelin, 1788",
   "nomeComumIngles": "Cliff Flycatcher",
   "periodoAtividade": "Diurno",
   "dimorfismo": "Não",
   "estadoConservacaoIucn": "Pouco Preocupante",
   "endemicaBrasil": "Não",
   "habitats": "Áreas urbanas, Áreas rurais, Campos e pastagens, Florestas e matas (úmidas, secas, ciliares etc.)",
   "dieta": "Artrópodes",
   "particula": "gibao-de-couro",
   "foto": true
 },
 {
   "id": 57,
   "ordem": "Passeriformes",
   "familia": "Tyrannidae",
   "nomeCientifico": "Camptostoma obsoletum",
   "nomeComumBrasileiro": "risadinha",
   "descricao": "Temminck, 1824",
   "nomeComumIngles": "Southern Beardless-Tyrannulet",
   "periodoAtividade": "Diurno",
   "dimorfismo": "Não",
   "estadoConservacaoIucn": "Pouco Preocupante",
   "endemicaBrasil": "Não",
   "habitats": "Florestas e matas (úmidas, secas, ciliares etc.), Cerrado e vegetação de savana",
   "dieta": "Artrópodes, Frutos",
   "particula": "risadinha",
   "foto": true
 },
 {
   "id": 58,
   "ordem": "Passeriformes",
   "familia": "Tyrannidae",
   "nomeCientifico": "Elaenia flavogaster",
   "nomeComumBrasileiro": "guaracava-de-barriga-amarela",
   "descricao": "Thunberg, 1822",
   "nomeComumIngles": "Yellow-bellied Elaenia",
   "periodoAtividade": "Diurno",
   "dimorfismo": "Não",
   "estadoConservacaoIucn": "Pouco Preocupante",
   "endemicaBrasil": "Não",
   "habitats": "Florestas e matas (úmidas, secas, ciliares etc.), Cerrado e vegetação de savana",
   "dieta": "Artrópodes, Frutos",
   "particula": "guaracava-de-barriga-amarela",
   "foto": true
 },
 {
   "id": 59,
   "ordem": "Passeriformes",
   "familia": "Tyrannidae",
   "nomeCientifico": "Suiriri suiriri",
   "nomeComumBrasileiro": "suiriri-cinzento",
   "descricao": "Vieillot, 1818",
   "nomeComumIngles": "Suiriri Flycatcher",
   "periodoAtividade": "Diurno",
   "dimorfismo": "Não",
   "estadoConservacaoIucn": "Pouco Preocupante",
   "endemicaBrasil": "Não",
   "habitats": "Campos e pastagens, Ambientes antrópicos (plantios, jardins, construções), Cerrado e vegetação de savana",
   "dieta": "Artrópodes, Frutos",
   "particula": "suiriri-cinzento",
   "foto": true
 },
 {
   "id": 60,
   "ordem": "Passeriformes",
   "familia": "Tyrannidae",
   "nomeCientifico": "Serpophaga subcristata",
   "nomeComumBrasileiro": "alegrinho",
   "descricao": "Vieillot, 1817",
   "nomeComumIngles": "White-crested Tyrannulet",
   "periodoAtividade": "Diurno",
   "dimorfismo": "Não",
   "estadoConservacaoIucn": "Pouco Preocupante",
   "endemicaBrasil": "Não",
   "habitats": "Florestas e matas (úmidas, secas, ciliares etc.), Cerrado e vegetação de savana",
   "dieta": "Artrópodes",
   "particula": "alegrinho",
   "foto": true
 },
 {
   "id": 61,
   "ordem": "Passeriformes",
   "familia": "Tyrannidae",
   "nomeCientifico": "Myiarchus swainsoni",
   "nomeComumBrasileiro": "irré",
   "descricao": "Cabanis & Heine, 1859",
   "nomeComumIngles": "Swainson's Flycatcher",
   "periodoAtividade": "Diurno",
   "dimorfismo": "Não",
   "estadoConservacaoIucn": "Pouco Preocupante",
   "endemicaBrasil": "Não",
   "habitats": "Florestas e matas (úmidas, secas, ciliares etc.), Cerrado e vegetação de savana",
   "dieta": "Artrópodes, Pequenos vertebrados",
   "particula": "irre",
   "foto": true
 },
 {
   "id": 62,
   "ordem": "Passeriformes",
   "familia": "Tyrannidae",
   "nomeCientifico": "Myiarchus ferox",
   "nomeComumBrasileiro": "maria-cavaleira",
   "descricao": "Gmelin, 1789",
   "nomeComumIngles": "Short-crested Flycatcher",
   "periodoAtividade": "Diurno",
   "dimorfismo": "Não",
   "estadoConservacaoIucn": "Pouco Preocupante",
   "endemicaBrasil": "Não",
   "habitats": "Florestas e matas (úmidas, secas, ciliares etc.), Cerrado e vegetação de savana",
   "dieta": "Artrópodes, Pequenos vertebrados",
   "particula": "maria-cavaleira",
   "foto": true
 },
 {
   "id": 63,
   "ordem": "Passeriformes",
   "familia": "Tyrannidae",
   "nomeCientifico": "Myiarchus tyrannulus",
   "nomeComumBrasileiro": "maria-cavaleira-de-rabo-enferrujado",
   "descricao": "Statius Muller, 1776",
   "nomeComumIngles": "Brown-crested Flycatcher",
   "periodoAtividade": "Diurno",
   "dimorfismo": "Não",
   "estadoConservacaoIucn": "Pouco Preocupante",
   "endemicaBrasil": "Não",
   "habitats": "Florestas e matas (úmidas, secas, ciliares etc.), Cerrado e vegetação de savana",
   "dieta": "Artrópodes, Pequenos vertebrados",
   "particula": "maria-cavaleira-de-rabo-enferrujado",
   "foto": true
 },
 {
   "id": 64,
   "ordem": "Passeriformes",
   "familia": "Tyrannidae",
   "nomeCientifico": "Pitangus sulphuratus",
   "nomeComumBrasileiro": "bem-te-vi",
   "descricao": "Linnaeus, 1766",
   "nomeComumIngles": "Great Kiskadee",
   "periodoAtividade": "Diurno",
   "dimorfismo": "Não",
   "estadoConservacaoIucn": "Pouco Preocupante",
   "endemicaBrasil": "Não",
   "habitats": "Áreas urbanas, Áreas rurais, Campos e pastagens, Florestas e matas (úmidas, secas, ciliares etc.)",
   "dieta": "Artrópodes, Frutos, Pequenos vertebrados",
   "particula": "bem-te-vi",
   "foto": true
 },
 {
   "id": 65,
   "ordem": "Passeriformes",
   "familia": "Tyrannidae",
   "nomeCientifico": "Machetornis rixosa",
   "nomeComumBrasileiro": "suiriri-cavaleiro",
   "descricao": "Vieillot, 1819",
   "nomeComumIngles": "Cattle Tyrant",
   "periodoAtividade": "Diurno",
   "dimorfismo": "Não",
   "estadoConservacaoIucn": "Pouco Preocupante",
   "endemicaBrasil": "Não",
   "habitats": "Campos e pastagens, Ambientes antrópicos (plantios, jardins, construções), Áreas urbanas",
   "dieta": "Artrópodes, Pequenos vertebrados",
   "particula": "suiriri-cavaleiro",
   "foto": true
 },
 {
   "id": 66,
   "ordem": "Passeriformes",
   "familia": "Tyrannidae",
   "nomeCientifico": "Myiodynastes maculatus",
   "nomeComumBrasileiro": "bem-te-vi-rajado",
   "descricao": "Statius Muller, 1776",
   "nomeComumIngles": "Streaked Flycatcher",
   "periodoAtividade": "Diurno",
   "dimorfismo": "Não",
   "estadoConservacaoIucn": "Pouco Preocupante",
   "endemicaBrasil": "Não",
   "habitats": "Florestas e matas (úmidas, secas, ciliares etc.), Cerrado e vegetação de savana",
   "dieta": "Artrópodes, Frutos",
   "particula": "bem-te-vi-rajado",
   "foto": true
 },
 {
   "id": 67,
   "ordem": "Passeriformes",
   "familia": "Tyrannidae",
   "nomeCientifico": "Megarynchus pitangua",
   "nomeComumBrasileiro": "neinei",
   "descricao": "Linnaeus, 1766",
   "nomeComumIngles": "Boat-billed Flycatcher",
   "periodoAtividade": "Diurno",
   "dimorfismo": "Não",
   "estadoConservacaoIucn": "Pouco Preocupante",
   "endemicaBrasil": "Não",
   "habitats": "Florestas e matas (úmidas, secas, ciliares etc.), Cerrado e vegetação de savana",
   "dieta": "Artrópodes, Frutos",
   "particula": "neinei",
   "foto": true
 },
 {
   "id": 68,
   "ordem": "Passeriformes",
   "familia": "Tyrannidae",
   "nomeCientifico": "Myiozetetes similis",
   "nomeComumBrasileiro": "bentevizinho-de-penacho-vermelho",
   "descricao": "Spix, 1825",
   "nomeComumIngles": "Social Flycatcher",
   "periodoAtividade": "Diurno",
   "dimorfismo": "Não",
   "estadoConservacaoIucn": "Pouco Preocupante",
   "endemicaBrasil": "Não",
   "habitats": "Florestas e matas (úmidas, secas, ciliares etc.), Cerrado e vegetação de savana",
   "dieta": "Artrópodes, Frutos",
   "particula": "bentevizinho-de-penacho-vermelho",
   "foto": true
 },
 {
   "id": 69,
   "ordem": "Passeriformes",
   "familia": "Tyrannidae",
   "nomeCientifico": "Tyrannus albogularis",
   "nomeComumBrasileiro": "suiriri-de-garganta-branca",
   "descricao": "Burmeister, 1856",
   "nomeComumIngles": "White-throated Kingbird",
   "periodoAtividade": "Diurno",
   "dimorfismo": "Não",
   "estadoConservacaoIucn": "Pouco Preocupante",
   "endemicaBrasil": "Não",
   "habitats": "Campos e pastagens, Ambientes antrópicos (plantios, jardins, construções), Cerrado e vegetação de savana",
   "dieta": "Artrópodes",
   "particula": "suiriri-de-garganta-branca",
   "foto": true
 },
 {
   "id": 70,
   "ordem": "Passeriformes",
   "familia": "Tyrannidae",
   "nomeCientifico": "Tyrannus melancholicus",
   "nomeComumBrasileiro": "suiriri",
   "descricao": "Vieillot, 1819",
   "nomeComumIngles": "Tropical Kingbird",
   "periodoAtividade": "Diurno",
   "dimorfismo": "Não",
   "estadoConservacaoIucn": "Pouco Preocupante",
   "endemicaBrasil": "Não",
   "habitats": "Campos e pastagens, Ambientes antrópicos (plantios, jardins, construções), Cerrado e vegetação de savana",
   "dieta": "Artrópodes",
   "particula": "suiriri",
   "foto": true
 },
 {
   "id": 71,
   "ordem": "Passeriformes",
   "familia": "Tyrannidae",
   "nomeCientifico": "Tyrannus savana",
   "nomeComumBrasileiro": "tesourinha",
   "descricao": "Daudin, 1802",
   "nomeComumIngles": "Southern Fork-tailed Flycatcher",
   "periodoAtividade": "Diurno",
   "dimorfismo": "Não",
   "estadoConservacaoIucn": "Pouco Preocupante",
   "endemicaBrasil": "Não",
   "habitats": "Campos e pastagens, Ambientes antrópicos (plantios, jardins, construções), Cerrado e vegetação de savana",
   "dieta": "Artrópodes",
   "particula": "tesourinha",
   "foto": true
 },
 {
   "id": 72,
   "ordem": "Passeriformes",
   "familia": "Tyrannidae",
   "nomeCientifico": "Empidonomus aurantioatrocristatus",
   "nomeComumBrasileiro": "peitica-de-chapéu-preto",
   "descricao": "d'Orbigny & Lafresnaye, 1837",
   "nomeComumIngles": "Crowned Slaty Flycatcher",
   "periodoAtividade": "Diurno",
   "dimorfismo": "Não",
   "estadoConservacaoIucn": "Pouco Preocupante",
   "endemicaBrasil": "Não",
   "habitats": "Campos e pastagens, Ambientes antrópicos (plantios, jardins, construções), Cerrado e vegetação de savana",
   "dieta": "Artrópodes",
   "particula": "peitica-de-chapeu-preto",
   "foto": true
 },
 {
   "id": 73,
   "ordem": "Passeriformes",
   "familia": "Tyrannidae",
   "nomeCientifico": "Empidonomus varius",
   "nomeComumBrasileiro": "peitica",
   "descricao": "Vieillot, 1818",
   "nomeComumIngles": "Variegated Flycatcher",
   "periodoAtividade": "Diurno",
   "dimorfismo": "Não",
   "estadoConservacaoIucn": "Pouco Preocupante",
   "endemicaBrasil": "Não",
   "habitats": "Campos e pastagens, Ambientes antrópicos (plantios, jardins, construções), Cerrado e vegetação de savana",
   "dieta": "Artrópodes",
   "particula": "peitica",
   "foto": true
 },
 {
   "id": 74,
   "ordem": "Passeriformes",
   "familia": "Tyrannidae",
   "nomeCientifico": "Fluvicola nengeta",
   "nomeComumBrasileiro": "lavadeira-mascarada",
   "descricao": "Linnaeus, 1766",
   "nomeComumIngles": "Masked Water-Tyrant",
   "periodoAtividade": "Diurno",
   "dimorfismo": "Não",
   "estadoConservacaoIucn": "Pouco Preocupante",
   "endemicaBrasil": "Não",
   "habitats": "Áreas urbanas, Áreas rurais, Campos e pastagens, Florestas e matas (úmidas, secas, ciliares etc.)",
   "dieta": "Artrópodes",
   "particula": "lavadeira-mascarada",
   "foto": true
 },
 {
   "id": 75,
   "ordem": "Passeriformes",
   "familia": "Tyrannidae",
   "nomeCientifico": "Pyrocephalus rubinus",
   "nomeComumBrasileiro": "príncipe",
   "descricao": "Boddaert, 1783",
   "nomeComumIngles": "Vermilion Flycatcher",
   "periodoAtividade": "Diurno",
   "dimorfismo": "Sim",
   "estadoConservacaoIucn": "Pouco Preocupante",
   "endemicaBrasil": "Não",
   "habitats": "Campos e pastagens, Ambientes antrópicos (plantios, jardins, construções), Cerrado e vegetação de savana",
   "dieta": "Artrópodes",
   "particula": "principe",
   "foto": true
 },
 {
   "id": 76,
   "ordem": "Passeriformes",
   "familia": "Tyrannidae",
   "nomeCientifico": "Nengetus cinereus",
   "nomeComumBrasileiro": "primavera",
   "descricao": "Vieillot, 1816",
   "nomeComumIngles": "Gray Monjita",
   "periodoAtividade": "Diurno",
   "dimorfismo": "Não",
   "estadoConservacaoIucn": "Pouco Preocupante",
   "endemicaBrasil": "Não",
   "habitats": "Campos e pastagens, Cerrado e vegetação de savana, Áreas abertas",
   "dieta": "Artrópodes",
   "particula": "primavera",
   "foto": true
 },
 {
   "id": 77,
   "ordem": "Passeriformes",
   "familia": "Vireonidae",
   "nomeCientifico": "Cyclarhis gujanensis",
   "nomeComumBrasileiro": "pitiguari",
   "descricao": "Gmelin, 1789",
   "nomeComumIngles": "Rufous-browed Peppershrike",
   "periodoAtividade": "Diurno",
   "dimorfismo": "Não",
   "estadoConservacaoIucn": "Pouco Preocupante",
   "endemicaBrasil": "Não",
   "habitats": "Capoeiras e matas secundárias, Bordas de mata, Cerrado e vegetação de savana",
   "dieta": "Artrópodes, Frutos",
   "particula": "pitiguari",
   "foto": true
 },
 {
   "id": 78,
   "ordem": "Passeriformes",
   "familia": "Corvidae",
   "nomeCientifico": "Cyanocorax cristatellus",
   "nomeComumBrasileiro": "gralha-do-campo",
   "descricao": "Temminck, 1823",
   "nomeComumIngles": "Curl-crested Jay",
   "periodoAtividade": "Diurno",
   "dimorfismo": "Não",
   "estadoConservacaoIucn": "Pouco Preocupante",
   "endemicaBrasil": "Não",
   "habitats": "Cerrado e vegetação de savana, Florestas e matas (úmidas, secas, ciliares etc.), Áreas urbanas",
   "dieta": "Artrópodes, Frutos, Pequenos vertebrados",
   "particula": "gralha-do-campo",
   "foto": true
 },
 {
   "id": 79,
   "ordem": "Passeriformes",
   "familia": "Corvidae",
   "nomeCientifico": "Cyanocorax chrysops",
   "nomeComumBrasileiro": "gralha-picaça",
   "descricao": "Vieillot, 1818",
   "nomeComumIngles": "Plush-crested Jay",
   "periodoAtividade": "Diurno",
   "dimorfismo": "Não",
   "estadoConservacaoIucn": "Pouco Preocupante",
   "endemicaBrasil": "Não",
   "habitats": "Florestas e matas (úmidas, secas, ciliares etc.), Bordas de mata, Ambientes antrópicos (plantios, jardins, construções)",
   "dieta": "Artrópodes, Frutos, Pequenos vertebrados",
   "particula": "gralha-picaca",
   "foto": true
 },
 {
   "id": 80,
   "ordem": "Passeriformes",
   "familia": "Hirundinidae",
   "nomeCientifico": "Pygochelidon cyanoleuca",
   "nomeComumBrasileiro": "andorinha-pequena-de-casa",
   "descricao": "Vieillot, 1817",
   "nomeComumIngles": "Blue-and-white Swallow",
   "periodoAtividade": "Diurno",
   "dimorfismo": "Não",
   "estadoConservacaoIucn": "Pouco Preocupante",
   "endemicaBrasil": "Não",
   "habitats": "Áreas urbanas, Ambientes antrópicos (plantios, jardins, construções), Bordas de mata",
   "dieta": "Artrópodes",
   "particula": "andorinha-pequena-de-casa",
   "foto": true
 },
 {
   "id": 81,
   "ordem": "Passeriformes",
   "familia": "Hirundinidae",
   "nomeCientifico": "Stelgidopteryx ruficollis",
   "nomeComumBrasileiro": "andorinha-serradora",
   "descricao": "Vieillot, 1817",
   "nomeComumIngles": "Southern Rough-winged Swallow",
   "periodoAtividade": "Diurno",
   "dimorfismo": "Não",
   "estadoConservacaoIucn": "Pouco Preocupante",
   "endemicaBrasil": "Não",
   "habitats": "Ambientes aquáticos e úmidos, Áreas abertas, Campos e pastagens",
   "dieta": "Artrópodes",
   "particula": "andorinha-serradora",
   "foto": true
 },
 {
   "id": 82,
   "ordem": "Passeriformes",
   "familia": "Hirundinidae",
   "nomeCientifico": "Progne tapera",
   "nomeComumBrasileiro": "andorinha-do-campo",
   "descricao": "Linnaeus, 1766",
   "nomeComumIngles": "Brown-chested Martin",
   "periodoAtividade": "Diurno",
   "dimorfismo": "Não",
   "estadoConservacaoIucn": "Pouco Preocupante",
   "endemicaBrasil": "Não",
   "habitats": "Campos e pastagens, Áreas abertas, Ambientes antrópicos (plantios, jardins, construções), Ambientes aquáticos e úmidos",
   "dieta": "Artrópodes",
   "particula": "andorinha-do-campo",
   "foto": true
 },
 {
   "id": 83,
   "ordem": "Passeriformes",
   "familia": "Hirundinidae",
   "nomeCientifico": "Progne chalybea",
   "nomeComumBrasileiro": "andorinha-grande",
   "descricao": "Gmelin, 1789",
   "nomeComumIngles": "Gray-breasted Martin",
   "periodoAtividade": "Diurno",
   "dimorfismo": "Sim",
   "estadoConservacaoIucn": "Pouco Preocupante",
   "endemicaBrasil": "Não",
   "habitats": "Áreas abertas, Áreas urbanas, Campos e pastagens, Ambientes antrópicos (plantios, jardins, construções)",
   "dieta": "Artrópodes",
   "particula": "andorinha-grande",
   "foto": true
 },
 {
   "id": 84,
   "ordem": "Passeriformes",
   "familia": "Hirundinidae",
   "nomeCientifico": "Tachycineta leucorrhoa",
   "nomeComumBrasileiro": "andorinha-de-sobre-branco",
   "descricao": "Vieillot, 1817",
   "nomeComumIngles": "White-rumped Swallow",
   "periodoAtividade": "Diurno",
   "dimorfismo": "Não",
   "estadoConservacaoIucn": "Pouco Preocupante",
   "endemicaBrasil": "Não",
   "habitats": "Áreas abertas, Bordas de mata, Campos e pastagens",
   "dieta": "Artrópodes",
   "particula": "andorinha-de-sobre-branco",
   "foto": true
 },
 {
   "id": 85,
   "ordem": "Passeriformes",
   "familia": "Troglodytidae",
   "nomeCientifico": "Troglodytes musculus",
   "nomeComumBrasileiro": "corruíra",
   "descricao": "Naumann, 1823",
   "nomeComumIngles": "Southern House Wren",
   "periodoAtividade": "Diurno",
   "dimorfismo": "Não",
   "estadoConservacaoIucn": "Não encontrado",
   "endemicaBrasil": "Não",
   "habitats": "Áreas urbanas, Ambientes antrópicos (plantios, jardins, construções), Capoeiras e matas secundárias, Bordas de mata",
   "dieta": "Artrópodes",
   "particula": "corruira",
   "foto": true
 },
 {
   "id": 86,
   "ordem": "Passeriformes",
   "familia": "Polioptilidae",
   "nomeCientifico": "Polioptila dumicola",
   "nomeComumBrasileiro": "balança-rabo-de-máscara",
   "descricao": "Vieillot, 1817",
   "nomeComumIngles": "Masked Gnatcatcher",
   "periodoAtividade": "Diurno",
   "dimorfismo": "Sim",
   "estadoConservacaoIucn": "Pouco Preocupante",
   "endemicaBrasil": "Não",
   "habitats": "Florestas e matas (úmidas, secas, ciliares etc.), Bordas de mata, Cerrado e vegetação de savana",
   "dieta": "Artrópodes",
   "particula": "balanca-rabo-de-mascara",
   "foto": true
 },
 {
   "id": 87,
   "ordem": "Passeriformes",
   "familia": "Turdidae",
   "nomeCientifico": "Turdus leucomelas",
   "nomeComumBrasileiro": "sabiá-barranco",
   "descricao": "Vieillot, 1818",
   "nomeComumIngles": "Pale-breasted Thrush",
   "periodoAtividade": "Diurno",
   "dimorfismo": "Não",
   "estadoConservacaoIucn": "Pouco Preocupante",
   "endemicaBrasil": "Não",
   "habitats": "Áreas urbanas, Florestas e matas (úmidas, secas, ciliares etc.), Ambientes antrópicos (plantios, jardins, construções), Cerrado e vegetação de savana",
   "dieta": "Frutos, Artrópodes",
   "particula": "sabia-barranco",
   "foto": true
 },
 {
   "id": 88,
   "ordem": "Passeriformes",
   "familia": "Turdidae",
   "nomeCientifico": "Turdus amaurochalinus",
   "nomeComumBrasileiro": "sabiá-poca",
   "descricao": "Cabanis, 1850",
   "nomeComumIngles": "Creamy-bellied Thrush",
   "periodoAtividade": "Diurno",
   "dimorfismo": "Não",
   "estadoConservacaoIucn": "Pouco Preocupante",
   "endemicaBrasil": "Não",
   "habitats": "Campos e pastagens, Capoeiras e matas secundárias, Áreas urbanas, Florestas e matas (úmidas, secas, ciliares etc.)",
   "dieta": "Frutos, Artrópodes",
   "particula": "sabia-poca",
   "foto": true
 },
 {
   "id": 89,
   "ordem": "Passeriformes",
   "familia": "Turdidae",
   "nomeCientifico": "Turdus subalaris",
   "nomeComumBrasileiro": "sabiá-ferreiro",
   "descricao": "Seebohm, 1887",
   "nomeComumIngles": "Eastern Slaty Thrush",
   "periodoAtividade": "Diurno",
   "dimorfismo": "Não",
   "estadoConservacaoIucn": "Pouco Preocupante",
   "endemicaBrasil": "Não",
   "habitats": "Capoeiras e matas secundárias, Bordas de mata, Florestas e matas (úmidas, secas, ciliares etc.)",
   "dieta": "Frutos, Artrópodes",
   "particula": "sabia-ferreiro",
   "foto": true
 },
 {
   "id": 90,
   "ordem": "Passeriformes",
   "familia": "Mimidae",
   "nomeCientifico": "Mimus saturninus",
   "nomeComumBrasileiro": "sabiá-do-campo",
   "descricao": "Lichtenstein, 1823",
   "nomeComumIngles": "Chalk-browed Mockingbird",
   "periodoAtividade": "Diurno",
   "dimorfismo": "Não",
   "estadoConservacaoIucn": "Pouco Preocupante",
   "endemicaBrasil": "Não",
   "habitats": "Campos e pastagens, Cerrado e vegetação de savana, Áreas urbanas, Áreas abertas",
   "dieta": "Artrópodes, Frutos",
   "particula": "sabia-do-campo",
   "foto": true
 },
 {
   "id": 91,
   "ordem": "Passeriformes",
   "familia": "Estrildidae",
   "nomeCientifico": "Estrilda astrild",
   "nomeComumBrasileiro": "bico-de-lacre",
   "descricao": "Linnaeus, 1758",
   "nomeComumIngles": "Common Waxbill",
   "periodoAtividade": "Diurno",
   "dimorfismo": "Não",
   "estadoConservacaoIucn": "Pouco Preocupante",
   "endemicaBrasil": "Não",
   "habitats": "Ambientes aquáticos e úmidos, Campos e pastagens",
   "dieta": "Sementes",
   "particula": "bico-de-lacre",
   "foto": true
 },
 {
   "id": 92,
   "ordem": "Passeriformes",
   "familia": "Passeridae",
   "nomeCientifico": "Passer domesticus",
   "nomeComumBrasileiro": "pardal",
   "descricao": "Linnaeus, 1758",
   "nomeComumIngles": "House Sparrow",
   "periodoAtividade": "Diurno",
   "dimorfismo": "Sim",
   "estadoConservacaoIucn": "Pouco Preocupante",
   "endemicaBrasil": "Não",
   "habitats": "Áreas urbanas, Áreas rurais, Ambientes antrópicos (plantios, jardins, construções)",
   "dieta": "Sementes, Artrópodes",
   "particula": "pardal",
   "foto": true
 },
 {
   "id": 93,
   "ordem": "Passeriformes",
   "familia": "Fringillidae",
   "nomeCientifico": "Euphonia chlorotica",
   "nomeComumBrasileiro": "fim-fim",
   "descricao": "Linnaeus, 1766",
   "nomeComumIngles": "Purple-throated Euphonia",
   "periodoAtividade": "Diurno",
   "dimorfismo": "Sim",
   "estadoConservacaoIucn": "Pouco Preocupante",
   "endemicaBrasil": "Não",
   "habitats": "Florestas e matas (úmidas, secas, ciliares etc.), Cerrado e vegetação de savana, Bordas de mata",
   "dieta": "Frutos, Sementes",
   "particula": "fim-fim",
   "foto": true
 },
 {
   "id": 94,
   "ordem": "Passeriformes",
   "familia": "Passerellidae",
   "nomeCientifico": "Ammodramus humeralis",
   "nomeComumBrasileiro": "tico-tico-do-campo",
   "descricao": "Bosc, 1792",
   "nomeComumIngles": "Grassland Sparrow",
   "periodoAtividade": "Diurno",
   "dimorfismo": "Não",
   "estadoConservacaoIucn": "Pouco Preocupante",
   "endemicaBrasil": "Não",
   "habitats": "Campos e pastagens, Cerrado e vegetação de savana, Áreas abertas",
   "dieta": "Sementes, Artrópodes",
   "particula": "tico-tico-do-campo",
   "foto": true
 },
 {
   "id": 95,
   "ordem": "Passeriformes",
   "familia": "Passerellidae",
   "nomeCientifico": "Zonotrichia capensis",
   "nomeComumBrasileiro": "tico-tico",
   "descricao": "Statius Muller, 1776",
   "nomeComumIngles": "Rufous-collared Sparrow",
   "periodoAtividade": "Diurno",
   "dimorfismo": "Não",
   "estadoConservacaoIucn": "Pouco Preocupante",
   "endemicaBrasil": "Não",
   "habitats": "Campos e pastagens, Áreas abertas, Áreas urbanas, Ambientes antrópicos (plantios, jardins, construções), Bordas de mata",
   "dieta": "Sementes, Artrópodes",
   "particula": "tico-tico",
   "foto": true
 },
 {
   "id": 96,
   "ordem": "Passeriformes",
   "familia": "Icteridae",
   "nomeCientifico": "Icterus pyrrhopterus",
   "nomeComumBrasileiro": "encontro",
   "descricao": "Vieillot, 1819",
   "nomeComumIngles": "Variable Oriole",
   "periodoAtividade": "Diurno",
   "dimorfismo": "Não",
   "estadoConservacaoIucn": "Pouco Preocupante",
   "endemicaBrasil": "Não",
   "habitats": "Florestas e matas (úmidas, secas, ciliares etc.), Ambientes aquáticos e úmidos, Bordas de mata, Ambientes antrópicos (plantios, jardins, construções)",
   "dieta": "Artrópodes, Frutos, Néctar",
   "particula": "encontro",
   "foto": true
 },
 {
   "id": 97,
   "ordem": "Passeriformes",
   "familia": "Icteridae",
   "nomeCientifico": "Molothrus bonariensis",
   "nomeComumBrasileiro": "chupim",
   "descricao": "Gmelin, 1789",
   "nomeComumIngles": "Shiny Cowbird",
   "periodoAtividade": "Diurno",
   "dimorfismo": "Sim",
   "estadoConservacaoIucn": "Pouco Preocupante",
   "endemicaBrasil": "Não",
   "habitats": "Áreas abertas, Campos e pastagens, Áreas urbanas, Áreas rurais",
   "dieta": "Artrópodes, Sementes",
   "particula": "chupim",
   "foto": true
 },
 {
   "id": 98,
   "ordem": "Passeriformes",
   "familia": "Icteridae",
   "nomeCientifico": "Pseudoleistes guirahuro",
   "nomeComumBrasileiro": "chupim-do-brejo",
   "descricao": "Vieillot, 1819",
   "nomeComumIngles": "Yellow-rumped Marshbird",
   "periodoAtividade": "Diurno",
   "dimorfismo": "Não",
   "estadoConservacaoIucn": "Pouco Preocupante",
   "endemicaBrasil": "Não",
   "habitats": "Ambientes aquáticos e úmidos, Campos e pastagens, Áreas abertas",
   "dieta": "Artrópodes, Sementes",
   "particula": "chupim-do-brejo",
   "foto": true
 },
 {
   "id": 99,
   "ordem": "Passeriformes",
   "familia": "Thraupidae",
   "nomeCientifico": "Nemosia pileata",
   "nomeComumBrasileiro": "saíra-de-chapéu-preto",
   "descricao": "Boddaert, 1783",
   "nomeComumIngles": "Hooded Tanager",
   "periodoAtividade": "Diurno",
   "dimorfismo": "Sim",
   "estadoConservacaoIucn": "Pouco Preocupante",
   "endemicaBrasil": "Não",
   "habitats": "Florestas e matas (úmidas, secas, ciliares etc.), Cerrado e vegetação de savana, Bordas de mata, Áreas abertas",
   "dieta": "Artrópodes, Frutos",
   "particula": "saira-de-chapeu-preto",
   "foto": true
 },
 {
   "id": 100,
   "ordem": "Passeriformes",
   "familia": "Thraupidae",
   "nomeCientifico": "Tersina viridis",
   "nomeComumBrasileiro": "saí-andorinha",
   "descricao": "Illiger, 1811",
   "nomeComumIngles": "Swallow Tanager",
   "periodoAtividade": "Diurno",
   "dimorfismo": "Sim",
   "estadoConservacaoIucn": "Pouco Preocupante",
   "endemicaBrasil": "Não",
   "habitats": "Florestas e matas (úmidas, secas, ciliares etc.), Bordas de mata, Áreas abertas, Ambientes antrópicos (plantios, jardins, construções)",
   "dieta": "Frutos, Néctar, Artrópodes",
   "particula": "sai-andorinha",
   "foto": true
 },
 {
   "id": 101,
   "ordem": "Passeriformes",
   "familia": "Thraupidae",
   "nomeCientifico": "Dacnis cayana",
   "nomeComumBrasileiro": "saí-azul",
   "descricao": "Linnaeus, 1766",
   "nomeComumIngles": "Blue Dacnis",
   "periodoAtividade": "Diurno",
   "dimorfismo": "Sim",
   "estadoConservacaoIucn": "Pouco Preocupante",
   "endemicaBrasil": "Não",
   "habitats": "Florestas e matas (úmidas, secas, ciliares etc.), Bordas de mata, Ambientes antrópicos (plantios, jardins, construções)",
   "dieta": "Frutos, Néctar, Artrópodes",
   "particula": "sai-azul",
   "foto": true
 },
 {
   "id": 102,
   "ordem": "Passeriformes",
   "familia": "Thraupidae",
   "nomeCientifico": "Coereba flaveola",
   "nomeComumBrasileiro": "cambacica",
   "descricao": "Linnaeus, 1758",
   "nomeComumIngles": "Bananaquit",
   "periodoAtividade": "Diurno",
   "dimorfismo": "Não",
   "estadoConservacaoIucn": "Pouco Preocupante",
   "endemicaBrasil": "Não",
   "habitats": "Áreas urbanas, Florestas e matas (úmidas, secas, ciliares etc.), Ambientes antrópicos (plantios, jardins, construções), Bordas de mata",
   "dieta": "Néctar, Frutos, Artrópodes",
   "particula": "cambacica",
   "foto": true
 },
 {
   "id": 103,
   "ordem": "Passeriformes",
   "familia": "Thraupidae",
   "nomeCientifico": "Volatinia jacarina",
   "nomeComumBrasileiro": "tiziu",
   "descricao": "Linnaeus, 1766",
   "nomeComumIngles": "Blue-black Grassquit",
   "periodoAtividade": "Diurno",
   "dimorfismo": "Sim",
   "estadoConservacaoIucn": "Pouco Preocupante",
   "endemicaBrasil": "Não",
   "habitats": "Campos e pastagens, Áreas abertas, Ambientes antrópicos (plantios, jardins, construções)",
   "dieta": "Sementes, Artrópodes",
   "particula": "tiziu",
   "foto": true
 },
 {
   "id": 104,
   "ordem": "Passeriformes",
   "familia": "Thraupidae",
   "nomeCientifico": "Coryphospingus cucullatus",
   "nomeComumBrasileiro": "tico-tico-rei",
   "descricao": "Statius Muller, 1776",
   "nomeComumIngles": "Red-crested Finch",
   "periodoAtividade": "Diurno",
   "dimorfismo": "Sim",
   "estadoConservacaoIucn": "Pouco Preocupante",
   "endemicaBrasil": "Não",
   "habitats": "Cerrado e vegetação de savana, Capoeiras e matas secundárias, Florestas e matas (úmidas, secas, ciliares etc.), Áreas abertas",
   "dieta": "Sementes, Artrópodes",
   "particula": "tico-tico-rei",
   "foto": true
 },
 {
   "id": 105,
   "ordem": "Passeriformes",
   "familia": "Thraupidae",
   "nomeCientifico": "Ramphocelus carbo",
   "nomeComumBrasileiro": "pipira-vermelha",
   "descricao": "Pallas, 1764",
   "nomeComumIngles": "Silver-beaked Tanager",
   "periodoAtividade": "Diurno",
   "dimorfismo": "Sim",
   "estadoConservacaoIucn": "Pouco Preocupante",
   "endemicaBrasil": "Não",
   "habitats": "Florestas e matas (úmidas, secas, ciliares etc.), Ambientes aquáticos e úmidos, Bordas de mata, Ambientes antrópicos (plantios, jardins, construções)",
   "dieta": "Frutos, Artrópodes",
   "particula": "pipira-vermelha",
   "foto": true
 },
 {
   "id": 106,
   "ordem": "Passeriformes",
   "familia": "Thraupidae",
   "nomeCientifico": "Sporophila lineola",
   "nomeComumBrasileiro": "bigodinho",
   "descricao": "Linnaeus, 1758",
   "nomeComumIngles": "Lined Seedeater",
   "periodoAtividade": "Diurno",
   "dimorfismo": "Sim",
   "estadoConservacaoIucn": "Pouco Preocupante",
   "endemicaBrasil": "Não",
   "habitats": "Campos e pastagens, Ambientes aquáticos e úmidos",
   "dieta": "Sementes",
   "particula": "bigodinho",
   "foto": true
 },
 {
   "id": 107,
   "ordem": "Passeriformes",
   "familia": "Thraupidae",
   "nomeCientifico": "Sporophila caerulescens",
   "nomeComumBrasileiro": "coleirinho",
   "descricao": "Vieillot, 1823",
   "nomeComumIngles": "Double-collared Seedeater",
   "periodoAtividade": "Diurno",
   "dimorfismo": "Sim",
   "estadoConservacaoIucn": "Pouco Preocupante",
   "endemicaBrasil": "Não",
   "habitats": "Campos e pastagens, Cerrado e vegetação de savana, Ambientes antrópicos (plantios, jardins, construções)",
   "dieta": "Sementes",
   "particula": "coleirinho",
   "foto": true
 },
 {
   "id": 108,
   "ordem": "Passeriformes",
   "familia": "Thraupidae",
   "nomeCientifico": "Thlypopsis sordida",
   "nomeComumBrasileiro": "saí-canário",
   "descricao": "d'Orbigny & Lafresnaye, 1837",
   "nomeComumIngles": "Orange-headed Tanager",
   "periodoAtividade": "Diurno",
   "dimorfismo": "Não",
   "estadoConservacaoIucn": "Pouco Preocupante",
   "endemicaBrasil": "Não",
   "habitats": "Florestas e matas (úmidas, secas, ciliares etc.), Bordas de mata, Cerrado e vegetação de savana",
   "dieta": "Artrópodes, Frutos",
   "particula": "sai-canario",
   "foto": true
 },
 {
   "id": 109,
   "ordem": "Passeriformes",
   "familia": "Thraupidae",
   "nomeCientifico": "Conirostrum speciosum",
   "nomeComumBrasileiro": "figuinha-de-rabo-castanho",
   "descricao": "Temminck, 1824",
   "nomeComumIngles": "Chestnut-vented Conebill",
   "periodoAtividade": "Diurno",
   "dimorfismo": "Sim",
   "estadoConservacaoIucn": "Pouco Preocupante",
   "endemicaBrasil": "Não",
   "habitats": "Capoeiras e matas secundárias, Bordas de mata, Ambientes antrópicos (plantios, jardins, construções)",
   "dieta": "Artrópodes, Frutos",
   "particula": "figuinha-de-rabo-castanho",
   "foto": true
 },
 {
   "id": 110,
   "ordem": "Passeriformes",
   "familia": "Thraupidae",
   "nomeCientifico": "Sicalis flaveola",
   "nomeComumBrasileiro": "canário-da-terra",
   "descricao": "Linnaeus, 1766",
   "nomeComumIngles": "Saffron Finch",
   "periodoAtividade": "Diurno",
   "dimorfismo": "Sim",
   "estadoConservacaoIucn": "Pouco Preocupante",
   "endemicaBrasil": "Não",
   "habitats": "Campos e pastagens, Áreas abertas, Áreas urbanas, Ambientes antrópicos (plantios, jardins, construções)",
   "dieta": "Sementes",
   "particula": "canario-da-terra",
   "foto": true
 },
 {
   "id": 111,
   "ordem": "Passeriformes",
   "familia": "Thraupidae",
   "nomeCientifico": "Thraupis sayaca",
   "nomeComumBrasileiro": "sanhaço-cinzento",
   "descricao": "Linnaeus, 1766",
   "nomeComumIngles": "Sayaca Tanager",
   "periodoAtividade": "Diurno",
   "dimorfismo": "Não",
   "estadoConservacaoIucn": "Pouco Preocupante",
   "endemicaBrasil": "Não",
   "habitats": "Áreas urbanas, Florestas e matas (úmidas, secas, ciliares etc.), Ambientes antrópicos (plantios, jardins, construções), Bordas de mata",
   "dieta": "Frutos, Artrópodes",
   "particula": "sanhaco-cinzento",
   "foto": true
 },
 {
   "id": 112,
   "ordem": "Passeriformes",
   "familia": "Thraupidae",
   "nomeCientifico": "Thraupis palmarum",
   "nomeComumBrasileiro": "sanhaço-do-coqueiro",
   "descricao": "Wied, 1821",
   "nomeComumIngles": "Palm Tanager",
   "periodoAtividade": "Diurno",
   "dimorfismo": "Não",
   "estadoConservacaoIucn": "Pouco Preocupante",
   "endemicaBrasil": "Não",
   "habitats": "Florestas e matas (úmidas, secas, ciliares etc.), Bordas de mata, Capoeiras e matas secundárias",
   "dieta": "Frutos, Artrópodes",
   "particula": "sanhaco-do-coqueiro",
   "foto": true
 },
 {
   "id": 113,
   "ordem": "Passeriformes",
   "familia": "Thraupidae",
   "nomeCientifico": "Stilpnia cayana",
   "nomeComumBrasileiro": "saíra-amarela",
   "descricao": "Linnaeus, 1766",
   "nomeComumIngles": "Burnished-buff Tanager",
   "periodoAtividade": "Diurno",
   "dimorfismo": "Sim",
   "estadoConservacaoIucn": "Pouco Preocupante",
   "endemicaBrasil": "Não",
   "habitats": "Florestas e matas (úmidas, secas, ciliares etc.), Bordas de mata, Ambientes antrópicos (plantios, jardins, construções)",
   "dieta": "Frutos, Artrópodes, Néctar",
   "particula": "saira-amarela",
   "foto": true
 }
]